httpie_gssapi.py
httpie_gssapi-1.0.2.dist-info/LICENSE
httpie_gssapi-1.0.2.dist-info/METADATA
httpie_gssapi-1.0.2.dist-info/WHEEL
httpie_gssapi-1.0.2.dist-info/entry_points.txt
httpie_gssapi-1.0.2.dist-info/top_level.txt
httpie_gssapi-1.0.2.dist-info/RECORD
