Metadata-Version: 2.1
Name: httpie-gssapi
Version: 1.0.2
Summary: GSSAPI authentication plug-in for HTTPie
Home-page: https://github.com/mprpic/httpie-gssapi
Author: Martin Prpic
Author-email: martin@nil.bz
License: MIT
Download-URL: https://github.com/mprpic/httpie-gssapi
Keywords: httpie gssapi kerberos
Platform: UNKNOWN
Classifier: Development Status :: 5 - Production/Stable
Classifier: Programming Language :: Python
Classifier: Programming Language :: Python :: 3
Classifier: Programming Language :: Python :: 3.6
Classifier: Programming Language :: Python :: 3.7
Classifier: Programming Language :: Python :: 3.8
Classifier: Programming Language :: Python :: 3.9
Classifier: Environment :: Plugins
Classifier: License :: OSI Approved :: MIT License
Classifier: Topic :: Internet :: WWW/HTTP
Classifier: Topic :: Utilities
License-File: LICENSE
Requires-Dist: httpie (>=0.9.7)
Requires-Dist: requests-gssapi (>=1.0.0)
